eeg_eyetracking_parser/__init__.py
eeg_eyetracking_parser/_custom_epochs.py
eeg_eyetracking_parser/_data2bids.py
eeg_eyetracking_parser/_eeg_preprocessing.py
eeg_eyetracking_parser/_parsing.py
eeg_eyetracking_parser/_time_frequency.py
eeg_eyetracking_parser/_triggers.py
eeg_eyetracking_parser/braindecode_utils.py
eeg_eyetracking_parser-0.16.6.dist-info/entry_points.txt
eeg_eyetracking_parser-0.16.6.dist-info/WHEEL
eeg_eyetracking_parser-0.16.6.dist-info/METADATA
eeg_eyetracking_parser-0.16.6.dist-info/RECORD
