Metadata-Version: 2.4
Name: eeg_eyetracking_parser
Version: 0.16.6
Summary: A Python module for reading concurrently recorded EEG and eye-tracking data,
Author-email: Hermine Berberyan <h.berberyan@rug.nl>, Wouter Kruijne <w.kruijne@rug.nl>, Sebastiaan Mathôt <s.mathot@cogsci.nl>, Ana Vilotjević <a.vilotijevic@rug.nl>
Requires-Python: >=3.5
Classifier: License :: OSI Approved :: GNU General Public License v3 or later (GPLv3+)
Requires-Dist: eyelinkparser
Requires-Dist: mne
Requires-Dist: autoreject
Requires-Dist: h5io
Requires-Dist: braindecode
Requires-Dist: python-picard
Requires-Dist: json_tricks
Project-URL: Documentation, https://github.com/smathot/eeg_eyetracking_parser
Project-URL: Source, https://github.com/smathot/eeg_eyetracking_parser
